ppvc/__init__.py
ppvc/ppvc.py
ppvc-1.0.0.dist-info/licenses/LICENSE
ppvc-1.0.0.dist-info/METADATA
ppvc-1.0.0.dist-info/WHEEL
ppvc-1.0.0.dist-info/entry_points.txt
ppvc-1.0.0.dist-info/top_level.txt
ppvc-1.0.0.dist-info/RECORD
