Metadata-Version: 2.4
Name: ppvc
Version: 1.0.0
Summary: A command-line utility for listing Python package versions from PyPI
Home-page: https://github.com/rapidrabbitsoft/ppvc
Author: Rapid Rabbit Software
Author-email: Rapid Rabbit Software <python@rapidrabbit.software>
Maintainer-email: Chris McMichael <python@apprabb.it>
License: BSD-2-Clause
Project-URL: Homepage, https://github.com/rapidrabbitsoft/ppvc
Project-URL: Repository, https://github.com/rapidrabbitsoft/ppvc
Project-URL: Bug Reports, https://github.com/rapidrabbitsoft/ppvc/issues
Project-URL: Source, https://github.com/rapidrabbitsoft/ppvc
Keywords: pypi,package,version,cli,utility
Classifier: Development Status :: 5 - Production/Stable
Classifier: Environment :: Console
Classifier: Intended Audience :: Developers
Classifier: Programming Language :: Python :: 3
Classifier: Programming Language :: Python :: 3.8
Classifier: Programming Language :: Python :: 3.9
Classifier: Programming Language :: Python :: 3.10
Classifier: Programming Language :: Python :: 3.11
Classifier: Programming Language :: Python :: 3.12
Classifier: Topic :: Software Development :: Libraries :: Python Modules
Classifier: Topic :: System :: Systems Administration
Classifier: Topic :: Utilities
Requires-Python: >=3.8
License-File: LICENSE
Requires-Dist: packaging>=23.0
Requires-Dist: rich>=13.0.0
Dynamic: author
Dynamic: home-page
Dynamic: license-file
Dynamic: requires-python
